{
    "app_hash": "7245de8e747a0d6fbe11f7cc14fcc0bb",
    "app_id": 8,
    "app_version": "8.5.2",
    "avatar": "null",
    "block": false,
    "blocked_untile": "",
    "device": "UMIDIGI Z2 Special Edition",
    "first_name": "Julia",
    "ipv6": false,
    "lang_pack": "ja",
    "last_check_time": 1676706242,
    "last_name": "Brochard",
    "layer": 151,
    "phone": "6283114246675",
    "proxy": [
        2,
        "proxy.froxy.com",
        9002,
        true,
        "76cOGpLSpjzCxmm7",
        "wifi;ca;;;"
    ],
    "register_time": 1676706242,
    "sdk": "Android 10 (29)",
    "session_file": "6283114246675",
    "sex": 0,
    "system_lang_pack": "ru",
    "twoFA": "qvFm9bYlzUPNu",
    "username": null
}